geodesicDome/__init__.py
geodesicDome/np_icosphere.py
geodesicDome-0.1.0.dist-info/METADATA
geodesicDome-0.1.0.dist-info/WHEEL
geodesicDome-0.1.0.dist-info/top_level.txt
geodesicDome-0.1.0.dist-info/RECORD
